pypsql/__init__.py
pypsql/connect.py
pypsql/ssh_connect.py
pypsql-0.0.4a0.dist-info/licenses/LICENSE.txt
pypsql-0.0.4a0.dist-info/METADATA
pypsql-0.0.4a0.dist-info/WHEEL
pypsql-0.0.4a0.dist-info/top_level.txt
pypsql-0.0.4a0.dist-info/RECORD
