Metadata-Version: 2.4
Name: pypsql
Version: 0.0.4a0
Summary: Functionality to connect and interact with PostgreSQL servers
Author-email: Marius Liebald <maliedvp@gmail.com>
Project-URL: Homepage, https://www.marius-liebald.com/pypsql/
Project-URL: Documentation, https://www.marius-liebald.com/pypsql/
Project-URL: Source Code, https://github.com/maliedvp/pypsql
Project-URL: Bug Tracker, https://github.com/maliedvp/pypsql/issues
Classifier: Environment :: Console
Classifier: Intended Audience :: Developers
Classifier: Intended Audience :: Information Technology
Classifier: Intended Audience :: Science/Research
Classifier: License :: OSI Approved :: MIT License
Classifier: Programming Language :: Python :: 3
Classifier: Topic :: Database
Requires-Python: >=3.8
License-File: LICENSE.txt
Requires-Dist: pandas>=2.2.3
Requires-Dist: sqlalchemy>=2.0.41
Requires-Dist: sshtunnel>=0.4.0
Requires-Dist: psycopg2-binary<3.0.0,>=2.9.10
Requires-Dist: python-dotenv>=1.1.1
Provides-Extra: postgres
Requires-Dist: psycopg2<3.0.0,>=2.9.10; extra == "postgres"
Provides-Extra: tests
Requires-Dist: pytest; extra == "tests"
Dynamic: license-file
